Metadata-Version: 2.1
Name: reepsy
Version: 0.0.1.1
Summary: Reepsy - simple library which solves classification pictures problem with machine learning
Home-page: https://github.com/ElishaFlacon/reepsy
Download-URL: https://github.com/ElishaFlacon/reepsy/archive/main.zip
Author: Elisha Flacon
License: BSD 3-Clause
Classifier: License :: OSI Approved :: BSD License
Classifier: Intended Audience :: Developers
Classifier: Programming Language :: Python :: 3.8
Classifier: Programming Language :: Python :: 3.9
Classifier: Programming Language :: Python :: 3.10
Requires-Python: >=3.8
License-File: LICENSE
